webdriver_installer/__init__.py
webdriver_installer/utils.py
webdriver_installer-1.0.0.dist-info/LICENSE.md
webdriver_installer-1.0.0.dist-info/METADATA
webdriver_installer-1.0.0.dist-info/WHEEL
webdriver_installer-1.0.0.dist-info/top_level.txt
webdriver_installer-1.0.0.dist-info/RECORD
