Metadata-Version: 2.1
Name: webdriver-installer
Version: 1.0.0
Summary: Download and install different web drivers
Author: riad-azz (Riadh Azzoun)
Author-email: <riadh.azzoun@hotmail.com>
Keywords: python,selenium,web,browser,webdriver installer,webdriver,download webdriver,geckodriver,operadriver,edgedriver,chromedriver
Classifier: Development Status :: 5 - Production/Stable
Classifier: Intended Audience :: Developers
Classifier: Programming Language :: Python :: 3
Classifier: Operating System :: Microsoft :: Windows
License-File: LICENSE.md
Requires-Dist: packaging
Requires-Dist: requests
Requires-Dist: beautifulsoup4
Requires-Dist: bs4
Requires-Dist: certifi
Requires-Dist: charset-normalizer
Requires-Dist: idna
Requires-Dist: pyparsing
Requires-Dist: soupsieve
Requires-Dist: urllib3
Requires-Dist: xmltodict
